{
  "id": "96-015",
  "year": 1996,
  "pdf_url": "https://fppc.ca.gov/content/dam/fppc/documents/advice-letters/1995-2015/1996/96-015.pdf",
  "pdf_sha256": "39a86eac2c5d38cae9dc073e2f684e35bf4941972ab3c4dbbd4308c104803de6",
  "local_pdf_path": "raw_pdfs/1996/96-015.pdf",
  "source_metadata": {
    "title_raw": "Year: 1996 Advice Letter # 96-015",
    "tags": [
      "Advice Letter",
      "1996"
    ],
    "scraped_at": "2026-01-31 16:39:14",
    "source_page_url": "https://fppc.ca.gov/advice/advice-opinion-search.html?SearchTerm=&tag1=/etc/tags/fppc/year/1996&tagCount=1"
  },
  "extraction": {
    "method": "native",
    "extracted_at": "2026-02-06T18:34:52.498052Z",
    "page_count": 4,
    "word_count": 1305,
    "char_count": 8383,
    "quality_score": 0.8,
    "olmocr_cost": null,
    "native_word_count": 1305
  },
  "content": {
    "full_text": "RAVI MEHTA\nCu IRM\nFAIR POLITICAL PRACTICES\nCOMMISSION\nJanuary 24,\n1996\nRoger Cochran\nStaff Toxicologist\nDepartment of Pesticide Regulation\n1020\nN Street\nSacramento, California\n95814\nRe:\nYour Request for Advice\nOur File No.\nA-96-015\nDear Mr.\nCochran:\nThis is in response to your request for advice regarding your\nresponsibilities as a designated public official under the gift\nand honoraria provisions of the Political Reform Act\n(the “Act”).\n1\nQUESTION\nMay a corporation pay travel expenses associated with your\nparticipation in a two—day workshop the corporation is sponsoring?\nCONCLUS ION\nPayments for transportation, related lodging and subsistence\nreceived in connection with participation in the workshop you have\ndescribed are gifts subject to the $280 annual limit on gifts.\nIn\naddition, if you accept the gifts,\nyou must disqualify yourself\nfrom any decision which will have a foreseeable material financial\neffect on DowElanco in the 12—month period after you receive the\ngifts.\n1\nGovernment Code Sections 81000-91015.\nAll statutory references\nare to the Government Code unless otherwise indicated.\nCommission\nregulations appear at\n2 California Code of Regulations,\nSections\n18000—18995.\n428 J STREET, SUITE 800, SACRAMENTO, CALIFORNIA 95814\n(916) 322-5660\n\n\nFile No.\nA—96—0l5\nPage\n2\nFACTS\nYou are a Staff Toxicologist (Specialist) with the California\nEnvironmental Protection Agency,\nDepartment of Pesticide\nRegulation.\nIn that capacity,\nDowElanco has asked you to\nparticipate in a workshop in North Carolina to identify research\nand information needed to better characterize the neurotoxic risk\nassociated with chlorpyrifos.\nThe principle objective of the\nworkshop is to identify the data requirements of regulatory\nagencies which will be needed to give an appropriate estimate of\nthese risks.\nYou were selected on the basis of both a publication\nyou authored on the risk of dietary exposure to chiorpyrifos and\nbecause you work for a governmental regulatory agency.\nThe workshop will consist of a series of discussions and\nbreak—out sessions.\nThe material you have sent us on the workshop\nindicates that there will be “leaders” and “facilitators” for each\nsession.\nYou will not be either a leader or facilitator, but\nDowElanco has requested you to be prepared to present information\nin the discussions about chlorpyrifos.\nIf you attend,\nDowElanco\nwill pay for your airfare to and from North Carolina and lodging\nexpenses associated with participating in the workshop.\nANALYSIS\nSection 89502(c)\nprovides that no designated employee of a\nstate agency shall accept an honorarium from any source.\nAn\nhonorarium is defined as any payment made in consideration for any\nspeech given, article published,\nor attendance at any public or\nprivate conference,\nconvention, meeting,\nsocial event,\nmeal,\nor\nlike gathering.\n(Section 89501(a).)\nYou have indicated that you are a designated employee of the\nDepartment of Pesticide Regulation.\nThus,\nyou may not receive an\nhonorarium in consideration for your participation in the\nworkshop.\n(Section 89502(c).)\nThe prohibition on receiving honoraria includes several\nexceptions that, as explained below,\ndo not apply in your case.\n(Section 89501(c); Regulations 18950.1 and 18950.3.)\nSection\n89506 provides,\namong other things, that payments, advances,\nor\nreimbursements for travel reasonably related to a legislative or\ngovernmental purpose or to an issue of state, national,\nor\ninternational public policy are not prohibited or limited if\neither the travel is in connection with a speech given or the\ntravel is provided by a governmental agency or bona fide nonprofit\nor educational institutions.\n(Section 89506(a).)\nRegulation\n18931.1 defines “speech given,” in relevant part, as “a public\naddress, oration, or other form of oral presentation,\nand includes\nparticipation in a panel,\nseminar,\nor debate.”\nThe exception in Section 89506(a)\ndoes not apply in this\ncase,\nhowever.\nThe travel will be provided by a private\ncorporation rather than a government or nonprofit organization.\n\n\nFile No.\nA—96—015\nPage\n3\nIn addition, the travel will not be in connection with a “speech\ngiven” as defined by Section 18931.1.\nIn your case,\nyou will be\nattending a two-day workshop.\nThe workshop will include a series\nof discussions and break—out sessions at which you will be sharing\ninformation in roundtable discussions.\nYou will not be either a\nleader or a facilitator in the discussions.\nMere participation in\na discussion group,\neven with advance preparation,\ndoes not\nqualify as a “speech given.”\n(Attwater Advice Letter,\nNo.\n95-168;\nHoehn Advice Letter,\nNo.\n1-92—392.)\nWhere the official is merely\nproviding information, rather than making a formal presentation,\nthe exception does not apply.\nSection 89506(d) (3)\nprovides another exception for payments\nreasonably connected with a “bona fide business, trade,\nor\nprofession” which satisfy “the criteria for federal income tax\ndeductions for business expenses specified in Sections 162 and 274\nof the Internal Revenue Code,\nare not honoraria or gifts unless\nthe sole or predominant activity of the business, trade,\nor\nprofession is making speeches.”\n(Section 89506(c); Regulation\n18950.1(e).)\nWhat constitutes a “bona fide profession” is not\nspecifically defined in the statute, however,\nexceptions in a\nstatute are to be strictly construed.\n(Julius Goldman’s Egg City\nv. Air Pollution Control Dept.\nof Ventura County\n(1981)\n116\nCal.App.3d 741.)\nTherefore,\nwe have applied the “bona fide\nbusiness, trade, or profession” exception only where the business\nor professional activity generates income independent of the\npublic official’s governmental employment or position.\n(See e.g.\nHodson Advice Letter, A-92-648; Hunter Advice Letter, A-93-203.)\nPayments for travel which do not fit within the exceptions\noutlined in Section 89506 are considered gifts subject to the gift\nlimits in Section 89503.\n(Section 89506(b).)\nSection 89503(c) provides that no member of a state board or\ncommission,\nand no designated employee of a state agency, shall\naccept gifts with a total value of more than two hundred eighty\ndollars\n($280)\nin a calendar year from any single source, if the\nmember or employee would be required to report the receipt of\nincome or gifts from that source on his or her statement of\neconomic interest.\nCertain general exceptions apply to the receipt of gifts.\nFor instance, free admission,\nand refreshments and similar non—\ncash nominal benefits provided to a filer during the entire event\nat which the filer gives a speech, participates in a panel or\nseminar,\nor provides a similar service,\nand actual intrastate\ntransportation and any necessary lodging and subsistence provided\ndirectly in connection with the speech, panel,\nseminar,\nor\nservice,\nincluding but not limited to meals and beverages on the\nday of the activity, are not payments and need not be reported by\nany filer.\n(Regulation 18950.3.)\nThe exception in Regulation 18950.3 is limited to\nparticipation in a speech, panel,\nseminar or similar service.\n\n\nFile No.\nA—96—015\nPage\n4\nMere participation in a discussion group is not included in the\nexception.\nAs a result, the payments will not fit into the\nexception in 18950.3 and are subject to the $280 limit on gifts to\na designated employee.\n2\nIn sum,\npayments you receive for travel and subsistence for\nparticipation in the workshop sponsored by DowElanco are gifts\nsubject to the $280 limit on gifts to a designated employee.\nPlease keep in mind that Sections 87100 and 87103(e)\nand\nRegulation 18940.1 require you to disqualify yourself from any\ndecision which will have a material financial effect on any donor\nof a gift of $280.\nTherefore,\nshould you choose to accept a gift\nof travel or subsistence from DowElanco,\nnot only will the gift be\nsubject to the $280 gift limit,\nbut you must disqualify yourself\nfrom cecisions which will have a material financial effect on\nDowElanco if the value of gifts received from DowElanco totals\n$280 during the\n12 months prior to the decision.\nIf you have any further questions, please feel free to\ncontact me at\n(916)\n322—5660.\nSincerely,\nSteven G.\nChurchwell\nGeneral Consel\n/ /\n)\n// /(\nBy:\nLiane ando1ph\nCounsel,\nLegal Division\nSGC:LR:ak\n2\nThe exception for a bona fide business, trade and profession in\nRegulation 18950.1 also applies to the gift limit, however, as\nnoted above, that exception is not applicable to this situation.\n",
    "full_text_markdown": null
  },
  "parsed": {
    "date": "1996-01-24",
    "date_raw": "January 24,\n1996",
    "requestor_name": "Cochran",
    "requestor_title": null,
    "requestor_city": null,
    "document_type": "advice_letter"
  },
  "sections": {
    "question": "May a corporation pay travel expenses associated with your\nparticipation in a two—day workshop the corporation is sponsoring?",
    "conclusion": "Payments for transportation, related lodging and subsistence\nreceived in connection with participation in the workshop you have\ndescribed are gifts subject to the $280 annual limit on gifts.\nIn\naddition, if you accept the gifts,\nyou must disqualify yourself\nfrom any decision which will have a foreseeable material financial\neffect on DowElanco in the 12—month period after you receive the\ngifts.\nCommission\nregulations appear at\n2 California Code of Regulations,\nSections\n18000—18995.\n\n(916) 322-5660\n\n\nFile No.\nA—96—0l5",
    "facts": "You are a Staff Toxicologist (Specialist) with the California\nEnvironmental Protection Agency,\nDepartment of Pesticide\nRegulation.\nIn that capacity,\nDowElanco has asked you to\nparticipate in a workshop in North Carolina to identify research\nand information needed to better characterize the neurotoxic risk\nassociated with chlorpyrifos.\nThe principle objective of the\nworkshop is to identify the data requirements of regulatory\nagencies which will be needed to give an appropriate estimate of\nthese risks.\nYou were selected on the basis of both a publication\nyou authored on the risk of dietary exposure to chiorpyrifos and\nbecause you work for a governmental regulatory agency.\nThe workshop will consist of a series of discussions and\nbreak—out sessions.\nThe material you have sent us on the workshop\nindicates that there will be “leaders” and “facilitators” for each\nsession.\nYou will not be either a leader or facilitator, but\nDowElanco has requested you to be prepared to present information\nin the discussions about chlorpyrifos.\nIf you attend,\nDowElanco\nwill pay for your airfare to and from North Carolina and lodging\nexpenses associated with participating in the workshop.",
    "analysis": "Section 89502(c)\nprovides that no designated employee of a\nstate agency shall accept an honorarium from any source.\nAn\nhonorarium is defined as any payment made in consideration for any\nspeech given, article published,\nor attendance at any public or\nprivate conference,\nconvention, meeting,\nsocial event,\nmeal,\nor\nlike gathering.\n(Section 89501(a).)\nYou have indicated that you are a designated employee of the\nDepartment of Pesticide Regulation.\nThus,\nyou may not receive an\nhonorarium in consideration for your participation in the\nworkshop.\n(Section 89502(c).)\nThe prohibition on receiving honoraria includes several\nexceptions that, as explained below,\ndo not apply in your case.\n(Section 89501(c); Regulations 18950.1 and 18950.3.)\nSection\n89506 provides,\namong other things, that payments, advances,\nor\nreimbursements for travel reasonably related to a legislative or\ngovernmental purpose or to an issue of state, national,\nor\ninternational public policy are not prohibited or limited if\neither the travel is in connection with a speech given or the\ntravel is provided by a governmental agency or bona fide nonprofit\nor educational institutions.\n(Section 89506(a).)\nRegulation\n18931.1 defines “speech given,” in relevant part, as “a public\naddress, oration, or other form of oral presentation,\nand includes\nparticipation in a panel,\nseminar,\nor debate.”\nThe exception in Section 89506(a)\ndoes not apply in this\ncase,\nhowever.\nThe travel will be provided by a private\ncorporation rather than a government or nonprofit organization.\n\n\nFile No.\nA—96—015\nIn addition, the travel will not be in connection with a “speech\ngiven” as defined by Section 18931.1.\nIn your case,\nyou will be\nattending a two-day workshop.\nThe workshop will include a series\nof discussions and break—out sessions at which you will be sharing\ninformation in roundtable discussions.\nYou will not be either a\nleader or a facilitator in the discussions.\nMere participation in\na discussion group,\neven with advance preparation,\ndoes not\nqualify as a “speech given.”\n(Attwater Advice Letter,\nNo.\n95-168;\nHoehn Advice Letter,\nNo.\n1-92—392.)\nWhere the official is merely\nproviding information, rather than making a formal presentation,\nthe exception does not apply.\nSection 89506(d) (3)\nprovides another exception for payments\nreasonably connected with a “bona fide business, trade,\nor\nprofession” which satisfy “the criteria for federal income tax\ndeductions for business expenses specified in Sections 162 and 274\nof the Internal Revenue Code,\nare not honoraria or gifts unless\nthe sole or predominant activity of the business, trade,\nor\nprofession is making speeches.”\n(Section 89506(c); Regulation\n18950.1(e).)\nWhat constitutes a “bona fide profession” is not\nspecifically defined in the statute, however,\nexceptions in a\nstatute are to be strictly construed.\n(Julius Goldman’s Egg City\nv. Air Pollution Control Dept.\nof Ventura County\n(1981)\n116\nCal.App.3d 741.)\nTherefore,\nwe have applied the “bona fide\nbusiness, trade, or profession” exception only where the business\nor professional activity generates income independent of the\npublic official’s governmental employment or position.\n(See e.g.\nHodson Advice Letter, A-92-648; Hunter Advice Letter, A-93-203.)\nPayments for travel which do not fit within the exceptions\noutlined in Section 89506 are considered gifts subject to the gift\nlimits in Section 89503.\n(Section 89506(b).)\nSection 89503(c) provides that no member of a state board or\ncommission,\nand no designated employee of a state agency, shall\naccept gifts with a total value of more than two hundred eighty\ndollars\n($280)\nin a calendar year from any single source, if the\nmember or employee would be required to report the receipt of\nincome or gifts from that source on his or her statement of\neconomic interest.\nCertain general exceptions apply to the receipt of gifts.\nFor instance, free admission,\nand refreshments and similar non—\ncash nominal benefits provided to a filer during the entire event\nat which the filer gives a speech, participates in a panel or\nseminar,\nor provides a similar service,\nand actual intrastate\ntransportation and any necessary lodging and subsistence provided\ndirectly in connection with the speech, panel,\nseminar,\nor\nservice,\nincluding but not limited to meals and beverages on the\nday of the activity, are not payments and need not be reported by\nany filer.\n(Regulation 18950.3.)\nThe exception in Regulation 18950.3 is limited to\nparticipation in a speech, panel,\nseminar or similar service.\n\n\nFile No.\nA—96—015\nMere participation in a discussion group is not included in the\nexception.\nAs a result, the payments will not fit into the\nexception in 18950.3 and are subject to the $280 limit on gifts to\na designated employee.\n2\nIn sum,\npayments you receive for travel and subsistence for\nparticipation in the workshop sponsored by DowElanco are gifts\nsubject to the $280 limit on gifts to a designated employee.\nPlease keep in mind that Sections 87100 and 87103(e)\nand\nRegulation 18940.1 require you to disqualify yourself from any\ndecision which will have a material financial effect on any donor\nof a gift of $280.\nTherefore,\nshould you choose to accept a gift\nof travel or subsistence from DowElanco,\nnot only will the gift be\nsubject to the $280 gift limit,\nbut you must disqualify yourself\nfrom cecisions which will have a material financial effect on\nDowElanco if the value of gifts received from DowElanco totals\n$280 during the\n12 months prior to the decision.",
    "question_synthetic": null,
    "conclusion_synthetic": null,
    "extraction_method": "regex_validated",
    "extraction_confidence": 0.9,
    "has_standard_format": true,
    "parsing_notes": "Mixed formats: modern, ocr"
  },
  "citations": {
    "government_code": [
      "81000",
      "87100",
      "89501(a)",
      "89501(c)",
      "89502(c)",
      "89503",
      "89503(c)",
      "89506",
      "89506(a)",
      "89506(b)",
      "89506(c)",
      "89506(d)(3)"
    ],
    "regulations": [
      "18931.1",
      "18940.1",
      "18950.1",
      "18950.3"
    ],
    "prior_opinions": [
      "A-92-648",
      "A-93-203",
      "A-95-168"
    ],
    "cited_by": [
      "02-207",
      "97-518",
      "98-152",
      "98-177"
    ],
    "external": [
      "116 Cal.App.3d 741"
    ]
  },
  "classification": {
    "topic_primary": "gifts_honoraria",
    "topic_secondary": null,
    "topic_tags": [],
    "confidence": 0.8333333333333334,
    "classified_at": "2026-02-06T18:34:52.498052Z",
    "classification_method": "heuristic:citation_based"
  },
  "embedding": {
    "qa_text": "QUESTION: May a corporation pay travel expenses associated with your\nparticipation in a two—day workshop the corporation is sponsoring?\n\nCONCLUSION: Payments for transportation, related lodging and subsistence\nreceived in connection with participation in the workshop you have\ndescribed are gifts subject to the $280 annual limit on gifts.\nIn\naddition, if you accept the gifts,\nyou must disqualify yourself\nfrom any decision which will have a foreseeable material financial\neffect on DowElanco in the 12—month period after you receive the\ngifts.\nCommission\nregulations appear at\n2 California Code of Regulations,\nSections\n18000—18995.\n\n(916) 322-5660\n\n\nFile No.\nA—96—0l5",
    "qa_source": "extracted",
    "first_500_words": "RAVI MEHTA Cu IRM FAIR POLITICAL PRACTICES COMMISSION January 24, 1996 Roger Cochran Staff Toxicologist Department of Pesticide Regulation 1020 N Street Sacramento, California 95814 Re: Your Request for Advice Our File No. A-96-015 Dear Mr. Cochran: This is in response to your request for advice regarding your responsibilities as a designated public official under the gift and honoraria provisions of the Political Reform Act (the “Act”). 1 QUESTION May a corporation pay travel expenses associated with your participation in a two—day workshop the corporation is sponsoring? CONCLUS ION Payments for transportation, related lodging and subsistence received in connection with participation in the workshop you have described are gifts subject to the $280 annual limit on gifts. In addition, if you accept the gifts, you must disqualify yourself from any decision which will have a foreseeable material financial effect on DowElanco in the 12—month period after you receive the gifts. 1 Government Code Sections 81000-91015. All statutory references are to the Government Code unless otherwise indicated. Commission regulations appear at 2 California Code of Regulations, Sections 18000—18995. 428 J STREET, SUITE 800, SACRAMENTO, CALIFORNIA 95814 (916) 322-5660 File No. A—96—0l5 Page 2 FACTS You are a Staff Toxicologist (Specialist) with the California Environmental Protection Agency, Department of Pesticide Regulation. In that capacity, DowElanco has asked you to participate in a workshop in North Carolina to identify research and information needed to better characterize the neurotoxic risk associated with chlorpyrifos. The principle objective of the workshop is to identify the data requirements of regulatory agencies which will be needed to give an appropriate estimate of these risks. You were selected on the basis of both a publication you authored on the risk of dietary exposure to chiorpyrifos and because you work for a governmental regulatory agency. The workshop will consist of a series of discussions and break—out sessions. The material you have sent us on the workshop indicates that there will be “leaders” and “facilitators” for each session. You will not be either a leader or facilitator, but DowElanco has requested you to be prepared to present information in the discussions about chlorpyrifos. If you attend, DowElanco will pay for your airfare to and from North Carolina and lodging expenses associated with participating in the workshop. ANALYSIS Section 89502(c) provides that no designated employee of a state agency shall accept an honorarium from any source. An honorarium is defined as any payment made in consideration for any speech given, article published, or attendance at any public or private conference, convention, meeting, social event, meal, or like gathering. (Section 89501(a).) You have indicated that you are a designated employee of the Department of Pesticide Regulation. Thus, you may not receive an honorarium in consideration for your participation in the workshop. (Section 89502(c).) The prohibition on receiving honoraria includes several exceptions that, as explained below, do not apply in your case. (Section 89501(c); Regulations 18950.1 and 18950.3.) Section 89506 provides, among other things, that payments, advances, or reimbursements for travel reasonably related to",
    "summary": null
  }
}