{
  "id": "96-023",
  "year": 1996,
  "pdf_url": "https://fppc.ca.gov/content/dam/fppc/documents/advice-letters/1995-2015/1996/96-023.pdf",
  "pdf_sha256": "1f68b18988c0464b9ffd73db862f67bf7b869c81c5897142b91064577ba5c5fe",
  "local_pdf_path": "raw_pdfs/1996/96-023.pdf",
  "source_metadata": {
    "title_raw": "Year: 1996 Advice Letter # 96-023",
    "tags": [
      "Advice Letter",
      "1996"
    ],
    "scraped_at": "2026-01-31 16:39:14",
    "source_page_url": "https://fppc.ca.gov/advice/advice-opinion-search.html?SearchTerm=&tag1=/etc/tags/fppc/year/1996&tagCount=1"
  },
  "extraction": {
    "method": "haiku_vision",
    "extracted_at": "2026-04-02T16:21:07.158734Z",
    "page_count": 5,
    "word_count": 1787,
    "char_count": 11192,
    "quality_score": 0.9830023670418836,
    "olmocr_cost": null,
    "native_word_count": 1789,
    "haiku_cost": 0.017644
  },
  "content": {
    "full_text": "RAVI MEHTA\nCHAIRMAN\n\nFAIR POLITICAL PRACTICES COMMISSION\n\nJanuary 26, 1996\n\nPeter J. Lucey\nAtkinson, Andelson, Loya,\nRudd & Romo\nThe Atrium, Suite 200\n5776 Stoneridge Mall Road\nPleasanton, California 94588\n\nRe: Your Request for Advice\nOur File No. A-96-023\n\nDear Mr. Lucey:\n\nThis is in response to your request for advice on behalf of\nMr. Fred Strauss, Mr. Franklyn E. Cole and Mr. R. G. Fagin,\nmembers of the Board of Trustees of the Jefferson School District\nin the City of Tracy, regarding the conflict-of-interest\nprovisions of the Political Reform Act (the \"Act\").¹ You are the\nattorney for the Board of Trustees.\n\nFACTS\n\nThe Mello-Roos Community Facilities District 89-2\n(\"M-R 89-2\") was formed within the Jefferson School District for\nthe purposes of funding school facilities construction. The\ngoverning board of M-R 89-2, referred to as TAPFFA, consists of\ntwo appointees from the Jefferson School Board and two appointees\nfrom the Tracy Union High School District Board. TAPFFA has been\nin existence since 1989 but has never levied a tax although it has\nauthority to impose an annual levy of $974 per dwelling unit.\n\nThe developer of a subdivision within M-R 89-2 has requested\nTAPFFA to offer an option to developers to pay the tax as a lump\nsum in advance and thereby release homeowners within their\nsubdivisions from the annual tax levy. The board of TAPFFA has\n\n________________________\n¹ Government Code Sections 81000-91015. All statutory references\nare to the Government Code unless otherwise indicated. Commission\nregulations appear at 2 California Code of Regulations, Sections\n18000-18995.\n\n428 J STREET, SUITE 800, SACRAMENTO, CALIFORNIA 95814 (916) 322-5660\n\nFile No. A-96-023\nPage 2\n\n\nindicated a willingness to consider such a concept and has\ninitiated a study to fix the amount for this prepayment option.\nThe estimates generated from this study have varied from $7,000 to\n$13,000 per dwelling. The developer has indicated he is willing\nto accept the prepayment option set by TAPFFA but has requested\nthat 23 homes he has already built be exempted from any liability\nfor the Mello-Roos tax. He has made this request through the\nJefferson Board of Trustees with the intention that the Board\nwill in turn direct its representatives on the TAPFFA Board to\ngrant the exemption.\n\nTwo of the current board members, Mr. Fagin and Mr. Strauss,\nhave purchased homes in the developer's subdivision which would be\nsubject to the Mello-Roos tax unless the exemptions sought by the\ndeveloper are granted. If the exemptions are granted as to the\nJefferson portion of the tax, Mr. Strauss and Mr. Fagin would only\npay the portion of the tax going towards high school facilities.\nMr. Fagin was assured, in writing by the developer at the time he\npurchased his home, that the developer would fully cover any\nMello-Roos liability.\n\nBoardmember Cole does not live within the subdivision;\nhowever, the developer leases space from Mr. Cole for his business\nand Mr. Cole anticipates employing the developer in the future.\n\nQUESTIONS\n\n1. Does Mr. Strauss, who is one of the two district\nappointees to the TAPFFA Board, Mr. Fagin, or Mr. Cole have\nconflicts of interest in voting on the proposed exemption?\n\n2. Does Mr. Strauss, Mr. Fagin, or Mr. Cole have conflicts\nof interest in voting on the proposed lump sum prepayment of the\ntax?\n\nCONCLUSION\n\n1. Yes, Mr. Strauss, Mr. Fagin and Mr. Cole must disqualify\nthemselves from the decision regarding the proposed exemption\nbecause the decision will have a reasonably foreseeable material\nfinancial effect on their real property interests and/or sources\nof income.\n\n2. Yes, the officials have a conflict of interest because\nthe decision regarding the lump sum payment is so interrelated to\nthe decision regarding the tax exemption that the officials must\ndisqualify themselves from both decisions.\n\nANALYSIS\n\nEconomic Interests\n\nSection 87100 of the Act prohibits any public official from\nmaking, participating in making, or otherwise using his or her\nofficial position to influence a governmental decision in which\nthe official has a financial interest.\n\nFile No. A-96-023\nPage 3\n\n\n     Section 87103 specifies that a public official has a\nfinancial interest in a decision if it is reasonably foreseeable\nthat the decision will have a material financial effect,\ndistinguishable from the effect on the public generally, on the\nofficial or a member of his or her immediate family or on:\n\n          (a) Any business entity in which the public\n     official has a direct or indirect investment worth one\n     thousand dollars ($1,000) or more.\n\n          (b) Any real property in which the public official\n     has a direct or indirect interest worth one thousand\n     dollars ($1,000) or more.\n\n          (c) Any source of income, other than gifts and\n     other than loans by a commercial lending institution in\n     the regular course of business on terms available to the\n     public without regard to official status, aggregating\n     two hundred fifty dollars ($250) or more in value\n     provided to, received by or promised to the public\n     official within 12 months prior to the time when the\n     decision is made.\n\n                                        (Section 87103.)\n\n     Mr. Fagin and Mr. Strauss each own a home in the subdivision\nat issue, presumably worth more than $1000 each. Accordingly,\nthey both have a real property interest which may be affected by\nthe board's decisions. (Section 87103(b).) Both Mr. Fagin and\nMr. Strauss must disqualify themselves from any decision which has\na reasonably foreseeable² material financial effect on their real\nproperty interest.\n\n     Mr. Cole does not own a home in the subdivision, but the\ndeveloper leases space from Mr. Cole for his business. Assuming\nthe developer has given Mr. Cole more than $250 in lease payments\nwithin the past twelve months, the developer is a source of income\nto him and Mr. Cole may not participate in any decision which will\nhave a reasonably foreseeable, material financial effect on the\ndeveloper. (Section 87103(c).)\n\nForeseeability and Materiality\n\n     Generally, each governmental decision is analyzed\nindependently to determine if there will be a foreseeable material\nfinancial effect on an official's financial interests. (In re\nOwen (1976) 2 FPPC Ops. 77.) Under some circumstances, however, a\n\n_____________________________\n     2\n     An effect is considered reasonably foreseeable if there is a\nsubstantial likelihood that it will occur. Certainty is not\nrequired. However, if an effect is only a mere possibility, it is\nnot reasonably foreseeable. (In re Thorner (1975) 1 FPPC Ops.\n198.)\n\nFile No. A-96-023\nPage 4\n\n\nseries of decisions may be too interrelated to be considered\nseparately. For example, if a decision concerning one portion of\na project could decide or alter the decision for which the\nofficial has a conflict of interest, the official would be\ndisqualified as to both decisions. (Nord Advice Letter, No. A-82-\n038.) In the Nord letter we advised that it was not possible to\nsegregate a decision to rezone fifteen lots into two decisions,\none decision to rezone the lot that was the source of the conflict\nand the other decision to rezone the remaining lots. We stated as\nfollows:\n\n     [t]he officials must disqualify themselves as to both\n     decisions if the result on one decision will effectively\n     determine the result of the other decision. This would\n     be true, for example, if the same policies and interests\n     are at stake in both decisions.\n\n     This would be the case here. You indicated in your letter\nthat the developer proposed the original idea of paying the lump\nsum tax up front. The board generated a study setting the amount\nfor the prepayment option and the developer indicated that he\nwould accept the proposal if the 23 homes he built were exempted\nfrom the Mello-Roos tax. The developer apparently requested the\nexemption as part of the negotiation process concerning the\nprepayment plan. One fact you have provided indicate that if one\npart of the plan is not approved, then the entire plan may not go\ninto effect or may be significantly altered. Thus, the decisions\nare intimately related and cannot be segregated. If the three\npublic officials you have mentioned are disqualified from one\ndecision, they will be disqualified from the other.\n\n     You have asked whether the public officials may participate\nin the decision to exempt 23 homes in the subdivision, including\nhomes owned by Mr. Fagin and Mr. Strauss, from the Mello-Roos tax.\nBoth Mr. Fagin and Mr. Strauss have direct real property interests\nin the subdivision which will be subject to the exemption if it\npasses. Regulation 18702.1 provides that an effect on an\nofficial's economic interest is material if the interest is\ndirectly involved in the decision. An interest in real property\nis directly involved if \"[t]he decision involves the imposition,\nrepeal or modification of any taxes or fees assessed or imposed on\nsuch property.\" (Regulation 18702.1(a)(3)(C).)\n\n     In this case, the decision will directly affect whether\nMr. Strauss' and Mr. Fagin's homes will be exempt from a tax. As\nsuch, the decision will have a foreseeable material financial\neffect on Mr. Fagin and Mr. Strauss' economic interests and they\nmust disqualify themselves. This is true even though the\ndeveloper has agreed to cover Mr. Fagin's tax liability because\nthe decision involves a tax on the property itself. If the\nexemption is not granted, the property will still have the tax\nliability, regardless of whether the developer ultimately pays the\ntax or defaults on his agreement to make the payment.\n\nFile No. A-96-023\nPage 5\n\nMr. Cole must disqualify himself from any decision which will\nhave a material financial effect on the developer because the\ndeveloper is a source of income to Mr. Cole. If the source of\nincome to the official is a party to the proceeding before the board,\nthen the source of income is directly involved and the\ndecision is deemed to have a material financial effect on the\nsource of income. (Regulation 18702.1(a)(1).) The developer is\ndirectly before the board seeking a tax exemption for 23 homes.\nMr. Cole must disqualify himself from the exemption decision.³\n\nYou have also asked whether the public officials may\nparticipate in the decision to permit the developer to pay all of\nthe Mello-Roos tax liability up front in a lump sum. As discussed\nabove, the decisions in this case are so interrelated that the\ndecisions cannot be separated for conflict-of-interest purposes.\nTherefore, all of the officials will be disqualified from both the\ndecision on the tax exemption and the lump sum payment plan.\n\nIf you have any further questions, please feel free to\ncontact me at (916) 322-5660.\n\nSincerely,\n\nSteven G. Churchwell\nGeneral Counsel\n\nBy: Liane Randolph\n    Counsel, Legal Division\n\nSGC:LR:ak\n\n\n³ A public official may not be disqualified from a decision if\nthe material financial effect on the official's interest is not\ndistinguishable from the effect on the public generally. (Section\n87103; Regulation 18703.) In this case, there are no facts to\nindicate that the public generally exception applies.",
    "full_text_markdown": null
  },
  "parsed": {
    "date": "1996-01-26",
    "date_raw": "January 26,\n1996",
    "requestor_name": "Lucey",
    "requestor_title": null,
    "requestor_city": null,
    "document_type": "advice_letter"
  },
  "sections": {
    "question": "1.\nDoes Mr.\nStrauss,\nwho is one of the two district\nappointees to the TAPFFA Board,\nMr.\nFagin,\nor Mr.\nCole have\nconflicts of interest in voting on the proposed exemption?\n2.\nDoes Mr.\nStrauss,\nMr.\nFagin,\nor Mr.\nCole have conflicts\nof interest in voting on the proposed limp sum prepayment of the\ntax?",
    "conclusion": "1.\nYes,\nMr.\nStrauss,\nMr.\nFagin and Mr.\nCole must disqualify\nthemselves from the decision regarding the proposed exemption\nbecause the decision will have a reasonably foreseeable material\nfinancial effect on their real property interests and/or sources\nof income.\n2.\nYes, the officials have a conflict of interest because\nthe decision regarding the lump sum payment is so interrelated to\nthe decision regarding the tax exemption that the officials must\ndisqualify themselves from both decisions.",
    "facts": "The Mello-Roos Community Facilities District 89-2\n(“M—R 89-2”)\nwas formed within the Jefferson School District for\nthe purposes of funding school facilities construction.\nThe\ngoverning board of M-R 89-2, referred to as TAPFFA,\nconsists of\ntwo appointees from the Jefferson School Board and two appointees\nfrom the Tracy Union High School District Board.\nTAPFFA has been\nin existence since 1989 but has never levied a tax although it has\nauthority to impose an annual levy of $974 per dwelling unit.\nThe developer of a subdivision within M-R 89—2 has requested\nTAPFFA to offer an option to developers to pay the tax as a lump\nsum in advance and thereby release homeowners within their\nsubdivisions from the annual tax levy.\nThe board of TAPFFA has\nCommission\nregulations appear at\n2 California Code of Regulations,\nSections\n18000—18995.\n\n(916) 322-5660\n\n\nFile No.\nA-96—023\nindicated a willingness to consider such a concept and has\ninitiated a study to fix the amount for this prepayment option.\nThe estimates generated from this study have varied from $7,000 to\n$13,000 per dwelling.\nThe developer has indicated he iswillirig\nto accept the prepayment option set by TAPFFA but has requested\nthat 23 homes he has already built be exempted from any liability\nfor the Mello-Roos tax.\nHe has made this request through the\nJefferson Board of Trustees with the intention that the Board\nwill,\nin turn, direct its representatives on the TAPFFA Board to\ngrant the exemption.\nTwo of the current board members,\nMr.\nFagin and Mr.\nStrauss,\nhave purchased homes in the developer’s subdivision which would be\nsubject to the Mello-Roos tax unless the exemptions sought by the\ndeveloper are granted.\nIf the exemptions are granted as to the\nJefferson portion of the tax,\nMr.\nStrauss and Mr.\nFagin would only\npay the portion of the tax going towards high school facilities.\nMr.\nFagin was assured,\nin writing by the developer at the time he\npurchased his home,\nthat’ the developer would fully cover any\nMello—Roos liability.\nBoardmember Cole does not live within the subdivision;\nhowever, the developer leases space from Mr.\nCole for his business\nand Mr.\nCole anticipates employing the developer in the future.",
    "analysis": "Economic Interests\nSection 87100 of the Act prohibits any public official from\nmaking, participating in making, or otherwise using his or her\nofficial position to influence a governmental decision in which\nthe official has a financial interest.\n\n\nFile No.\nA—96—023\nSection 87103 specifies that •a public official has a\nfinancial interest in a decision if it is reasonably foreseeable\nthat the decision will have a material financial effect,\ndistinguishable from the effect on the public generally,\non the\nofficial or a member of his or her immediate family or on:\n(a)\nAny business entity in which the public\nofficial has a direct or indirect investment worth one\nthousand dollars\n($1,000)\nor more.\n(b)\nAny real property in which the public official\nhas a direct or indirect interest worth one thousand\ndollars\n($1,000)\nor more.\n(c)\nAny source of income, other than gifts and\nother than loans by a commercial lending institution in\nthe regular course of business on terms available to the\npublic without regard to official status, aggregating\ntwo hundred fifty dollars\n($250)\nor more in value\nprovided to, received by or promised to the public\nofficial within 12 months prior to the time when the\ndecision is made.\n(Section 87103.)\nMr.\nFagin and Mr.\nStrauss each own a home in the subdivision\nat issue, presumably worth more than $1000 each.\nAccordingly,\nthey both have a real property interest which may be affected by\nthe Board’s decisions.\n(Section 87103(b).)\nBoth Mr.\nFagin and\nMr.\nStrauss must disqualify themselves from any decision which has\na reasonably foreseeable\n2 material financial effect on their real\nproperty interest.\nMr.\nCole does not own a home in the subdivision, but the\ndeveloper leases space from Mr.\nCole for his business.\nAssmuing\nthe developer has given Mr.\nCole more than $250 in lease payments\nwithin the past twelve months, the developer is a source of income\nto him and Mr.\nCole may not participate in any decision which will\nhave a reasonably foreseeable, material financial effect on the\ndeveloper.\n(Section 87103(c).)\nForeseeability and Materiality\nGenerally, each governmental decision is analyzed\nindependently to determine if there will be a foreseeable material\nfinancial effect on an official’s financial interests.\n(In re\nOwen\n(1976)\n2\nFPPC Ops.\n77.)\nUnder some circumstances,\nhowever,\na\n2\nAn effect is considered reasonably foreseeable if there is a\nsubstantial likelihood that it will occur.\nCertainty is not\nrequired.\nHowever, if an effect is only a mere possibility, it is\nnot reasonably foreseeable.\n(In re Thorner\n(1975)\n1 FPPC Ops.\n198.)\n\n\nFile No.\nA—96--023\nseries of decisions may be too interrelated to be considered\nseparately.\nFor example, if a decision concerning one portion of\na project could decide or alter the decision for which the\nofficial has a conflict of interest, the official would be\ndisqualified as to both decisions.\n(Nord Advice Letter,\nNo. A-82-\n038.)\nIn the Nord letter we advised that it was not possible to\nsegregate a decision to rezone fifteen lots into two decisions,\none decision to rezone the lot that was the source of the Conflict\nand the other decision to rezone the remaining lots.\nWe stated as\nfollows:\n[t]he officials must disqualify themselves as to both\ndecisions if the result on one decision will effectively\ndetermine the result of the other decision.\nThis would\nbe true,\nfor example, if the same policies and interests\n•are at stake in both decisions.\nThis would be the case here.\nYou indicated in your letter\nthat the developer proposed the original idea of paying the lump\nsum tax up front.\nThe board generated a study setting the amount\nfor the prepayment option and the developer indicated that he\nwould accept the proposal if the 23 homes he built were exempted\nfrom the Mello-Roos tax.\nThe developer apparently requested the\nexemption as part of the negotiation process concerning the\nprepayment plan.\nThe facts you have provided indicate that if one\npart of the plan is not approved,\nthen the entire plan may not go\ninto effect or may be significantly altered.\nThus, the decisions\nare intimately related and cannot be segregated.\nIf the three\npublic officials you have mentioned are disqualified from one\ndecision, they will be disqualified from the other.\nYou have asked whether the public officials may participate\nin the decision to exempt 23 homes in the subdivision,\nincluding\nhomes owned by Mr.\nFagin and Mr. Strauss,\nfrom the Mello—Roos tax.\nBoth Mr.\nFagin and Mr.\nStrauss have direct real property interests\nin the subdivision which will be subject to the exemption if it\npasses.\nRegulation 18702.1 provides that an effect on an\nofficial’s economic interest is material if the interest is\ndirectly involved in the decision.\nAn interest in real property\nis directly involved if “[t]he decision involves the, imposition,\nrepeal or modification of any taxes or fees assessed or imposed on\nsuch property.”\n(Regulation 18702.1(a) (3) (C).)\nIn this case, the decision will directly affect whether\nMr.\nStrauss’ and Mr.\nFagin’s homes will be exempt from a tax.\nAs\nsuch, the decision will have a foreseeable material financial\neffect on Mr.\nFagin and Mr. Strauss’ economic interests and they\nmust disqualify themselves.\nThis is true even though the\ndeveloper has agreed to cover Mr. Fagin’s tax liability because\nthe decision involves a tax on the property itself.\nIf the\nexemption is not granted, the property will still have the tax\nliability, regardless of whether the developer ultimately pays the\ntax or defaults on his agreement to make the payment.\n\n\nFile No.\nA—96—023\nMr.\nCole must disqualify himself from any decision which will\nhave a material financial effect on the developer because the\ndeveloper is a source of income to Mr.\nCole.\nIf the source of\nincome to the official is a party to the proceeding before the\nboard, then the source of income is directly involved and the\ndecision is deemed to have a material financial effect on the\nsource of income.\n(Regulation 18702.l(a)(l).)\nThe developer is\ndirectly before the board seeking a tax exemption for 23 homes.\nMr.\nCole must disqualify himself from the exemption decision.\n3\nYou have also asked whether the public officials may\nparticipate in the decision to permit the developer to pay all of\nthe Mello-Roos tax liability up front in a lump sum.\nAs discussed\nabove,\nthe decisions in this case are so interrelated that the\ndec.isions cannot be separated for conflict—of—interest purposes.\nTherefore, all of the officials will be disqualified from both the\ndecision on the tax exemption and the lump sum payment plan.\nIf you have any furtherquestions, please feel free to\ncontact me at\n(916)\n322-5660.",
    "question_synthetic": null,
    "conclusion_synthetic": null,
    "extraction_method": "regex_validated",
    "extraction_confidence": 0.9,
    "has_standard_format": true,
    "parsing_notes": "Format: modern"
  },
  "citations": {
    "government_code": [
      "81000",
      "87100",
      "87103",
      "87103(b)",
      "87103(c)"
    ],
    "regulations": [
      "18702",
      "18702.1",
      "18703"
    ],
    "prior_opinions": [],
    "cited_by": [],
    "external": [
      "In re Owen(1976)2 FPPC Ops. 77",
      "In re Thorner(1975)1 FPPC Ops. 198"
    ]
  },
  "classification": {
    "topic_primary": "conflicts_of_interest",
    "topic_secondary": null,
    "topic_tags": [],
    "confidence": 0.8,
    "classified_at": "2026-02-06T18:34:52.563559Z",
    "classification_method": "heuristic:citation_based"
  },
  "embedding": {
    "qa_text": "QUESTION: 1.\nDoes Mr.\nStrauss,\nwho is one of the two district\nappointees to the TAPFFA Board,\nMr.\nFagin,\nor Mr.\nCole have\nconflicts of interest in voting on the proposed exemption?\n2.\nDoes Mr.\nStrauss,\nMr.\nFagin,\nor Mr.\nCole have conflicts\nof interest in voting on the proposed limp sum prepayment of the\ntax?\n\nCONCLUSION: 1.\nYes,\nMr.\nStrauss,\nMr.\nFagin and Mr.\nCole must disqualify\nthemselves from the decision regarding the proposed exemption\nbecause the decision will have a reasonably foreseeable material\nfinancial effect on their real property interests and/or sources\nof income.\n2.\nYes, the officials have a conflict of interest because\nthe decision regarding the lump sum payment is so interrelated to\nthe decision regarding the tax exemption that the officials must\ndisqualify themselves from both decisions.",
    "qa_source": "extracted",
    "first_500_words": "RAVI MEHTA CHAIRMAN FAIR POLITICAL PRACTICES COMMISSION January 26, 1996 Peter J. Lucey Atkinson, Andelson, Loya, Rudd & Romo The Atrium, Suite 200 5776 Stoneridge Mall Road Pleasanton, California 94588 Re: Your Request for Advice Our File No. A-96-023 Dear Mr. Lucey: This is in response to your request for advice on behalf of Mr. Fred Strauss, Mr. Franklyn E. Cole and Mr. R. G. Fagin, members of the Board of Trustees of the Jefferson School District in the City of Tracy, regarding the conflict-of-interest provisions of the Political Reform Act (the \"Act\").¹ You are the attorney for the Board of Trustees. FACTS The Mello-Roos Community Facilities District 89-2 (\"M-R 89-2\") was formed within the Jefferson School District for the purposes of funding school facilities construction. The governing board of M-R 89-2, referred to as TAPFFA, consists of two appointees from the Jefferson School Board and two appointees from the Tracy Union High School District Board. TAPFFA has been in existence since 1989 but has never levied a tax although it has authority to impose an annual levy of $974 per dwelling unit. The developer of a subdivision within M-R 89-2 has requested TAPFFA to offer an option to developers to pay the tax as a lump sum in advance and thereby release homeowners within their subdivisions from the annual tax levy. The board of TAPFFA has ________________________ ¹ Government Code Sections 81000-91015. All statutory references are to the Government Code unless otherwise indicated. Commission regulations appear at 2 California Code of Regulations, Sections 18000-18995. 428 J STREET, SUITE 800, SACRAMENTO, CALIFORNIA 95814 (916) 322-5660 File No. A-96-023 Page 2 indicated a willingness to consider such a concept and has initiated a study to fix the amount for this prepayment option. The estimates generated from this study have varied from $7,000 to $13,000 per dwelling. The developer has indicated he is willing to accept the prepayment option set by TAPFFA but has requested that 23 homes he has already built be exempted from any liability for the Mello-Roos tax. He has made this request through the Jefferson Board of Trustees with the intention that the Board will in turn direct its representatives on the TAPFFA Board to grant the exemption. Two of the current board members, Mr. Fagin and Mr. Strauss, have purchased homes in the developer's subdivision which would be subject to the Mello-Roos tax unless the exemptions sought by the developer are granted. If the exemptions are granted as to the Jefferson portion of the tax, Mr. Strauss and Mr. Fagin would only pay the portion of the tax going towards high school facilities. Mr. Fagin was assured, in writing by the developer at the time he purchased his home, that the developer would fully cover any Mello-Roos liability. Boardmember Cole does not live within the subdivision; however, the developer leases space from Mr. Cole for his business and Mr. Cole anticipates employing the developer in the future. QUESTIONS 1. Does Mr. Strauss, who is one of the",
    "summary": null
  }
}