{
  "id": "03-006",
  "year": 2003,
  "pdf_url": "https://fppc.ca.gov/content/dam/fppc/documents/advice-letters/1995-2015/2003/03-006.pdf",
  "pdf_sha256": "55e07a196cb2a3950647d1bc8aed5565dafedbc91dc66a6e47500750e948258f",
  "local_pdf_path": "raw_pdfs/2003/03-006.pdf",
  "source_metadata": {
    "title_raw": "Year: 2003 Advice Letter # 03-006",
    "tags": [
      "2003",
      "Advice Letter"
    ],
    "scraped_at": "2026-01-31 14:39:15",
    "source_page_url": "https://fppc.ca.gov/advice/advice-opinion-search.html?SearchTerm=&tag1=/etc/tags/fppc/year/2003&tagCount=1&page=21"
  },
  "extraction": {
    "method": "native",
    "extracted_at": "2026-02-06T18:34:22.801388Z",
    "page_count": 11,
    "word_count": 4125,
    "char_count": 27030,
    "quality_score": 0.7175,
    "olmocr_cost": null,
    "native_word_count": 4125
  },
  "content": {
    "full_text": "Re\nFeln PorrrrcAt. PnacrrcEs CouvrrssroN\n428 J Street. Suite 620 . Sacramento, CA g5gl4-2329\n(916) 322-5660. Fax (916) 322-0886\nMarch 11,2003\nH. Peter Klein, County Counsel\nOffice of the County Counsel\n501 Low Gap Road, Room 1030\nUkiah, CA95482\nYour Request for Advice\nOur File No. A-03-006\nDear Mr. Klein:\nThis letter is in response to your request for advice on behalf of Richard\nShoemaker, Supervisor for the Second Diskict of the Mendocino County Board of\nSupervi.sors, regarding the conflict of interest provisions of the Political Reform Act (the\n'Act').1\nQUESTIONS\nl. \nDoes Supervisor Shoemaker have a conflict of interest disqualifring him\nfrom making,particrpating in making or influencing a vote on the Ukiah Valley Area\nPlan (\"UVAP'), based on his economic interest in his personal residence and the\nimprovements to the access road to his residence that would accompany approval ofthe\nUVAP?\n2. \nDoes Supervisor Shoemaker have a conflict of interest disqualifring him\nfrom making, particrpating in making or influencing a vote on the UVAP, based o, his\neconomic interest in a client who is a source of income to him in excess of $500 over the\npast 12 months, and who has an option to purchase properfy within the UVAP area and\nseeks rezoning of that property from agricultural to residential for the building of low-\nincorne housing, or from the portion of the TIVAP dealing with that decision, if that\ndecision is segregated from the rest of the UVAP?\nrGovemmentCodesections8l000-91014. \nCommissionregulationsappearatTitle2,sectionsl8l0g-\n18997, ofthe California Code ofRegulations.\nffi\n\n\nFile No. 4-03-006\nPage No. 2\n3. \nDoes Supervisor Shoemakerhave a conflict of interest disqualifring him\nfrom making,particrpating in making or influencing a vote on the UVAP, based on his\neconomic interest in other clients within the TIVAP area who may be sources of income\nequal to or greaterthan $500 within the last 12 months?\n4. \nDoes Supervisor Shoemaker have a conflict of interest disqualiffing him\nfrom making, participatingin making or influencing a vote on the UVAP, based on his\neconomic interest in his business, Green Lion Landscape Services, which, among other\nthings, provides services to clients within the UVAP area?\nCONCLUSIONS\n1. \nNo, unless it is reasonably foreseeable that the improvements to the access\nroad that would result from the development of the 80-acreparcel adjacent to his property\nwould have amaterial financial effect on the value of his properfy, sufficient to rebut the\npresumption o f non-m ateiality .\n2. \nYes. The rural housing development corporation initiated aproceeding\nbefore Supervisor Shoemaker's board and is a source of income in excess of $500 over\nthe past 12 months to him. Therefore, the corporation is directly involved in a\ngovernmental decision before Supervisor Shoemaker's board, and his conflict of interest\nis disqualiffing.\n3. \nPossibly, depending on the applicable materiality standard.\n4. \nNo. Supervisor Shoemakerhas determined that the materiality standard\napplicable to his business wjll not be met. Therefore, there is no disqualifyingconflict of\ninterest present related to Green Lion.\nFACTS\nThe following facts were provided in your original letter and in subsequent\ntelephone conversations with Commission staffon March 10,2003.\nSupervisor Richard Shoemaker represents the2n District of Mendocino County.\nSupervisor Shoemaker has been a county supervisor for six years. IIis district is about\n7.5 square miles in a counQr of approximately 3,500 square miles in size. Roughly 80%\nof thepopulation of the 2\"d district lives within the boundaries of the City of Uiciah. The\nCity of tlkiah is wholly contained in the 2\"d district.\nThe county has undertaken the process of reviewing and possibly implementing\nthe Ukiah Valley Area Plan (\"UVAP'). This plan, when and if adopted, will be a part of\nthe Mendocino County General Plan. The City of Ukiah is excluded from the UVAP\nbecause the board of supervisors has no planning authority over the City of Ukiah.\n\n\nFileNo. ,4.-03-006\nPage No. 3\nThe UVAP is intended, when adopted, to provide comprehensive,long-term\npolicy direction for growth and development in the Ukiah Valley. The UVAP addresses\nfive of seven elements required by state law, excluding noise and housing. The three\nmajor elements of the plan are:\nResearch Elements: Open space and conservation, historic and archaeological\nsafety and energy.\nfnfrastructure Elements: Airport, community facilities and services, parks and\nrecreation, circulation and transportation.\nDevelopment Elements: Community design and land use.\nSupervisor Shoemaker owns a 1.Zi-aqeparcel within the city limits of Ukiah. It\nis his principal residence and the location of his landscape contracting business, He has\nowned this property since 1990. His property lies approximately 550 feet from aportion\nof the unincorporated county area included in the Ukiah Valley Area PIan.\nThere is an SO-acre parcel approximately 550 feet from Supervisor Shoemaker's\nreal property, which is currently undeveloped and is the subject of a possible zoning\ndesignation change in the UVAP.\nSupervisor Shoemaker's property is accessed by a substandard two-lane road at\nthis time. The road then continues through the SO-acre undeveloped parcel that would be\nincluded in the UVAP. The city has plans to widen the road and connect it to a main east-\nwest street 1,100 feet to the east. The UVAP will propose the county cooperate and\npafiicipate in this upgrade, through financial and regulatory support. It will then be\ndesignated as a main roadway connecting the only existing east-west corridor to a more\neasterly, shorter but important east-west corridor. As development occurs, road\nimprovement will be required to occur on at least TOYo of the road Supervisor\nShoemaker's property faces. The 70oh of the road on which improvernent will be\nrequired to occur will be the county portion of the road associated with the 80-acre\nparcel; Supervisor Shoemaker's property is fronted by aportion of the road owned by the\ncity.\nSupervisor Shoemaker also owns a landscape contracting company which is\noperated as a sole,proprietorship. This business provides installation and landscape\nmaintenance services. The business, Green Lion Landscape Services (\"Green Lion')\nprovides services to client properties within the UVAP area.\nA client of Green Lion, which, as clarified in ourMarch l0,2003,telephone\nconversation, is a source of income to Supervisor Shoemaker in excess of $500 over the\nTast 72 months, has an option agreernent to purchase real property in the UVAP are4\nwhich the client wants redesignated and rezoned from agricultural to residential. This\noption agreement has not yet been exercised. This client has also been in discussion with\nlandowners within 550 feet of Supervisor Shoemaker's real property to acquire that\n\n\nFile No. 4-03-006\nPage No. 4\nproperty. No agreernent has been entered into between these parties for that property.\nThis client is a rural housing development corporation, which acquires real property for\nresale to low-income persons. This corporation also assists low-income persons to build\nhouses on this property. The property and houses are owned, ultimatelS by persons other\nthan the development corporation. Neighboring property to the property for which an\noption to purchase exists, the Olga Hudson subdivision in the UVAP area, was aproperty\noriginally owned by the development corporation and is now owned by private residents.\nSupervisor Shoemaker does not provide landscaping services to residents of this\nsubdivision, nor does Supervisor Shoemakerprovide services to properties owned by the\ndevelopment corporation in the UVAP area.\nSupervisor Shoemakerprovides landscape services to other clients with real\nproperty ownership in the UVAP area, some of whom maybe sources of income equal to\nor in excess of $500 over the past 12 months, according to facts obtained by telephone on\nMarch 70,2003. With respect to these clients, Supervisor Shoemaker has represented\nthat no board of supervisor's decision involving action of the IIVAP, will result in an\nincrease or decrease in Green Lion's gross revenues for a fiscal year in the amount of\n$20,000 or more; nor will the board's decision result in Green Lion incurring or avoiding\nadditional expenses or reducing or eliminating existing expenses for a fiscal year in the\namount of $5,000 or more; nor will the board's decision result in an increase or decrease\nin the value of Green Lion's assets or liabilities of Green Lion by $20,000 ormore.\nAITALYSIS\nThe primary purpose for the conflict of interest provisions of the Act is to ensure\nthat \"[p]ublic officials, whether elected or appointed, [should] perform their duties in an\nimpartial manner, free from bias caused by their own financial interests or the financial\ninterests ofpersons who have supported them.\" (Section S1001(b).) In furtherance of\nthis goal, section 87100 of the Act prohibits a public official from making, participating\nin making, or otherwise using his or her official position to influence a governmental\ndecision in which the official has a financial interest.\nDetermining whether a conflict of interest exists under section 87100 requires\nanalysis of the following questions as outlined below.2\nStep One: Is Supervisor Shoemaker a \"public officialrr?\nAs a member of the Mendocino County Board of Supervisors, Supervisor\nShoemaker is a \"mernber, officer, employee or consultant of a state or local government\nagency\" and, therefore, is subject to the conflict of interest provisions of the Act.\n(Section 82048; regulation 1 8701 (a).)\n' These questions are based on the Act's conflict-of-interest analysis provided at Regulation 18700(b).\n\n\nFile No. A-03-006\nPage No. 5\nstep Two: rs supervisor shoemaker making, participating in making or\ninfluencing a governmental decision?\nAs a member of the board of supervisors, Supervisor Shoemaker will \"make a\ngovernmental decision\" if he votes on the UVAP. (Section 87l}l;regulations 18702 and\n18702.1.)\nStep Three: 'What are Supervisor Shoemaker's economic interests - \nthe possible\nsources of a conflict of interest?\nSection 87103 provides that apublic official has a \"financial interest\" in a\ngovernmental decision'lf it is reasonably foreseeable that the decision will have a\nmateriaT financial effect, distingu'ishable from its effect on thepublic generally,on the\nofficial, a member ofhis orher immediate family,\" or on any ofthe official's economic\ninterests, described as follows:\nA public official has an economic interest in a business entity in which he or she\nhas a direct orindirect investment 3 of $2,000 ormore (section 87103(a);\nRegulation 18703.1(a)); or in which he or she is a director, officer, parhrer,\ntrustee, employee, or holds any position of management (section 87103(d);\nregulation I 8703. 1(b));\na\na\nA public official has an economic interest in real property in which he or she has a\ndirect or indirect interest of $2,000 or more (section 87103(b); regulation\n187O3.2);\nA public official has an economic interest in.any source of income, including\npromised income, which aggregates to $500 ormore within 12 months prior to the\ndecision (section 87 I 03 (c); regulation I 87 03 .3);\nA public official has an economic interest in any source of gifts to him or her if\nthe gifts aggregate to $340 or more within 12 months prior to the decision\n(section 871 03(e); regulation 1870. .9;\nA public official has an economic interest in his or her personal finances,\nincluding those of his or her immediate family .. this is the \"personal financial\neffects\" rule (section 87103; regulation 13703,5).\nSupervisor Shoemaker has an economic interest in his personal residence and the\nsurrounding properfy, assuming he has a direct or indirect investment of $2,000 or more\nin the property and the strucfure. He has an economic interest in his business, Green Lion\n3 An indirect investment or interest means aoy investrnent or interest owned by the spouse of an official or\nby a mernber of the official's immediate family, by an agent on behalf of a public official, or by a business entity or\ntrust in which the official, the official's immediate family, or their agents own directly, indirectly, or beneficially a\nl0-percent interest or greater. (Section 87103.) \"Immediate family\" is defined at Section 820i9 as an official;s\nspouse and dependent children.\n\n\nFile No. A-03-006\nPage No. 6\nLandscaping Services. Supervisor Shoemaker also has an economic interest in the\nunnamed client that is a rural housing development corporation (\"Development\nCorporation') that seeks therezoning of theproperty within the UVAP areato which it\nholds an option to purchase, as well as in any other clients who are sources of income\nequal to or in excess of $500 for the 12 months preceding the decision.\nStep f,'our: Are the economic interests of Supervisor Shoemaker directly or\nindirectly involved in the goyernmental decisions?\nReal Property\nReal property is directly involved in a govemmental decision if anypart of that\nreal property is located within 500 feet of the boundaries (orproposed boundaries) of the\nreal property which is the \"subject ofthe govemmental decision.,a\nSupervisor Shoemaker's property is located beyond 500 feet of the S0-acre parcel\nthat will be included within the UVAP, which presumptively makes the property\nindirectly involved. Under ordinary circumstances, this would be the end of the analysis\nas to whether Supervisor Shoemaker's property was directly or indirectly involved in the\ngovemmental decision. However, this is an unusual situation in which there is a\nsecondary decision imbedded within the larger decision that is even more significant to\nthe analysis than the larger decision.\nIn this case, the UVAP contains the proposal that the county \"cooperate\" with the\ncity in the improvement of the access road to Supervisor Shoemaker's residence, and\nover the course of the development of the 80-acre parcel ofproperty adjacent to\nSupervisor Shoemaker's land, approximately TOYo of the road Supervisor Shoemaker,s\nproperty faces, although not the portion directly in front ofhis property, will undergo\nimprovement, and the road will be designated a main roadway, and connecting it to an\nimportant east-west corridor.\nUnder these facts, because the county portion of the road that will be improved as\na result of development of the 80-acre parcel is the same 550 feet from his property as the\nS0-acre parcel, itself, Supervisor Shoemaker's property is indirectly involved in this\ndecision, as we11.5\nRegulation lSTW.2provides several other situations in which an official's real property is considered\n\"directly involved\" in a governmental decision. (lS7M.2(a)(2)-(6).) None of these appear to appiy to Supervisor\nShoemaker's facts.\n5 Regulation lS7}4.2(b)provides: \"(b) Notwithstanding subdivision (a) above, real property in which a\npublic official has an interest is not directly involved in a govemmental decision, but is indirecily involved if: . . . (2)\nThe decision solely concerns repairs, replacement, or maintenance of existing streets, water, sewer, storm drainage or\nsimilar facilities.\" This regulation does not apply to determine that Supervisor Shoemaker's property is indirectl!\ninvolved, because the decision at issue does not \"solely concem repairs, replacement, or maintenance\" of an existing\nroad. Rather, the road will be substantially improved as a result of the decision on the (IVAP, which will lead to\ndevelopment ofthe SO-acre parcel ofproperty adjacent to Supervisor shoemaker's properly.\n\n\nFile No. 4-03-006\nPage No. 7\nSources of Income and Supervisor Shoemakerrs Business\nThe same definition is applicable to sources of income and to business entities to\ndetermine whether they are directly or indirectly involved in a governmental decision.\nSet forth at regulation 18704.1(a)(1) and Q), it states:\n\"(a) A person, including business entities, sources of\nincome, and sources of gifts, is directly involved in a\ndecision before an official's agency when that person,\neither directly or by an agent:\n\"(I) Initiates the proceeding in which the decision will be\nmade by filing an application, claim, appeal, or similar\nrequest or;\n\"(2) Is a named party in, or is the subject o{, the\nproceeding conceming the decision before the official or\nthe official's agency. A person is the subject of a\nproceeding if a decision involves the issuance, renewal,\napproval, denial or revocation of any license, permit or\nother entitlement to, or contract with, the subject person.,,\nBased on this definition, the Development Corporation client is directly involved\nin the governmental decision, because it has initiated a proceeding to have property\nrezoned and redesignated from agricultural to residential. Any other sources of income to\nSupervisor Shoemaker who fall within the definition listed above would,likewise, be\ndirectly involved in a govemmental decision. For those sources ofincome.who have\nneither initiated a proceeding nor are the subject of a proceeding, as defined above, those\npersons are indirectly involved in the decision.\nLikewise, Supervisor Shoemaker's business, Green Lion Landscape Services, has\ninitiated no proceeding and is not a named party in,nor is the subject of the proceeding\nconcerning the UVAP decision, according to the facts with which we have been\npresented. Therefore, Green Lion is indirectly involved.\nSteps Five and Six: What are the applicable materiality standards and is it\nreasonably foreseeable that the financial effect of the governmental decision upon\nSupervisor Shoemaker's economic interests will meet these materiality standards?\nReal Property\nMateriality Standard: The financial effect of a govemmental decision on real\nproperty which is indirectly involved in the goveflrmental decision is presumed not to be\nmaterial. (Regulatio n 187 05.2@)( 1 ).) That regulation continues:\n\n\nFile No. A-03-006\nPage No. 8\n\"This presumptiolnfi:u.y be rebutted byproof thatthere are\nspecific circumstances regarding the governmental\ndecision, its financial effect, and the nature of the real\nproperty in which the public official has an economic\ninterest, which make it reasonably foreseeable that the\ndecision will have amateial financial efi[ect on the real\nproperty in which the public official has an interest.\nExamples of specific circumstances that will be considered\nincludg but are not limited to, circumstances where the\ndecision aflects:\n\"(A) The development potential or income producing\npotential of the real property in which the official has an\neconomic interest;\n\"(B) The use of the real property in which the official has\nan economic interest;\n\"(C) The character of the neighborhood including, but not\nlimited to, substantial effects on: traffic, view, privacy,\nintensity ofuse, noise levels, air emissions, or similar traits\nof the neighborhood.\"\nIn considering these circumstances for rebuttal, it should be remembered that\nmaterial financial effect can mean either an increase or a decrease in property value or\nenjoyment for the owner/occupant of the property.\nIn this case, there may be some issues related to the road improvements and\nupgrades associated with the development of the S0-acre parcel adjacent to Supervisor\nShoemaker's property that may be sufficient to rebut the presumption of non-materiality.\nWe lack sufficient facts to analyze this issue further, but hightight the relevant regulations\nfor your review and analysis.\nSources of Income\nA. \nDevelopment Corporation: Because this source of income is directly\ninvolved in a govemmental decision before supavisor Shoemaker,s board, the\nmateriality standard set forth at regulation 18705.3(a) applies:\n\"Directly involved sources of income. Any reasonably\nforeseeable financial effect on a person who is a source of\nincome to a public official, and who is directly involved in\na decision before the official's agency, is deemed material.,,\nB. \nIndirectly fnvolved Sources of Ineome: Because these sources of\nincome are unidentified and unenumerated, this query having been added in ourMarch\n\n\nFile No. ,4.-03-006\nPage No. 9\n10,2003, telephone conversation, we can do no more than give a generaloverview of the\nregulations for your information. The materiality standardsfor this category of economic\ninterest can be found at regulation 18705.3(b) (copy encloseo. For indiiecily involved\nsources of income which are business entities, the materiality standards set forth in\nregulation 18705.1(c). This regulation sets forth a series ofmateriality thresholds, based\non the size of the business entity. For indirectly involved sogrces ofincome which are\nnon-profit entities, including governmental entities, regulation 18705.3(b)(2)(A)-(F) sets\nforth varying threshold amounts, depending on the entity's gross urr.rui i\"\"iiptr and the\nmeasurable financial effect of the decision on entity's income. For indirectly involved\nsources of income who are individuals:\n\"(3) . . . The effect of a decision is material as to an\nindividual who is a source ofincome to an official if any of\nthe following applies:\n\"(A) The decision will affect the individual,s income,\ninvestments or other tangible or intangible assets or\nliabilities (other than real property) by $1,000 or more; or\n\"(B) The decision will affect the individua|s rear property\ninterest in a manner that is considered material unaer iitte\n2, Califomia Code of Regulations, sections 1 g705.2(b).,,\nRegulation 18705.2(b), referenced above, sets forth the materiality standard for a public\nofficial's indirectly involved real property interests.\nSupervisor Shoemaker,s Business Enti8\nThe materiality standards for an indirectly involved business entity in which a\npublic official has an economic interest are found at regulation 18705.1(c), which sets\nforth varyrng materiality thresholds, based on the size of the business. dupervisor\nShoemaker has represented that \"no board of supervisor's decision involving action of\nthe UVAP, will result in an increase or decrease in Green Lion's gross reveriues for a\nfiscal year in the amount of $20,000 or more; nor will the board's decision result in\nGreen Lion incurring or avoiding additional expenses orreducing or eliminating existing\nexpenses for a fiscal year in the amount of $5,000 or more; nor will the board,s decision\nresult in an increase or decrease in the value of Green Lion's assets or liabilities of Green\nLion by $20,000 or more.\" Therefore, it appears that Supervisor Shoemaker has\nreviewed regulation 18705.1(c), and determined that his business is not covered by\nsubdivisions (c)(1)-(3), and that Green Lion falls into subdivision (c)(4) of regulation\n1 8705. 1, which provides:\n\"If the business entity is not covered by subdivisions (c)(l)-\n(3), the financial effect of a governmental decision on the\nbusiness entity is material if it is reasonably foreseeable\nthat:\n\n\nFile No. 4-03-006\nPageNo. l0\n\"(A) The governmental decision will result in an increase\nor decrease in the business entity's gross revenues for a\nfiscal year in the amount of $20,000 ormore; or,\n\"(B) The governmental decision will result in the business\nentity incurring or avoiding additional expenses or reducing\nor eliminating existing expenses for a fiscal year in the\namount of $5,000 or more; or,\n\"(C) The governmental decision will result in an increase\nor decrease in the value of the business entity,s assets or\nliabilities of $20,000 ormore.\"\nSupervisor Shoemakerhas determined that this materiality standard will not be\nmet.\nReasonable Foreseeability: An effect upon economic interests is considered\n\"reasonably foreseeable\" if there is a substantial likelihood that it will occur. (Regulation\n18706(a).) A financial effect need not be certain to be considered reasonably foreieeable,\nbut it must be more than a mere possibility. Qn re Thorner (1975) I FppC Ops. l9g.)\nThe determination of whether or not it is reasonably foreseeable that the\nmateriality standard will be met is necessarily a factual question that is ultimately for the\npublic official to decide.\nSegmentation of Decision: Please note that for purposes of determining\nconflicts of interest under the Act, governmental decisions are analyzed indepenJently to\ndetermine if there will be a foreseeable and material financial efiteci on apublic official,s\neconomic interest. (In re Owen (1976) 2 FPPC Ops.77.) Therefore, under certain\ncircumstances, a public official disqualified from one decision may participate in other\nrelated decisions, provided that the official's participation in the lattir does not affect the\ndecision in which he or she has a disqualifying conflict of interest. (SweeneyAdvice\nLetter, No. A-89-639.) Some decisions are too interrelated to be considered sqlarately so\nthat the official's conflict of interest on one decision will be disqualifting for the other.\n(Kilian Advice Letter, No. 4-89-522; Mtller Advice Letter, No. 4-82-11-9.) However, if\na governmental decision may be logically segregated, the public body maTrproceduraliy\nsegregate the decision prior to allowing the public official to participate.u -We \ndo not\n6 The Commission has previously advised public officials that the procedural segregation must include the\nfollowing three steps: (1) the decision in which the public official has a disqualifying fina-nci-al interest should be\nsegregated from the other decisions on the public body's agenda; (2) the decision-should be considered first and a final\ndecision should be reached without the disqualified official's participation; and (3) once a final decision has been\nreached, the disqualified ofificial may participate in the other decisions so tong as fils or her participation does not result\nin re-opening the previous decision, or in any other way affect the decision from which rtre ofnciaiwas disqualified.\n(Ennis Adice Letter, No. A-94-203.)\n\n\nFile No. 4-03-006\nPage No. 11\nhave enough information regarding the decisions before Supervisor Shoemaker to\ndetermine whether the segmentation procedure will be necessary or useful to him.\nSteps Seven and Eight: 66Public Generally\" and \"Legally Required participation,\nExceptions\nStep seven is an exception that applies when the reasonably foreseeable and\nmaterial financial effect on an official's economic interest is not distinguishable from the\neffect on the public generally. (Section 83ll2;regulation 18707.) Stei-eight is an\nexcqrtion that applies when the official's participation is legally requirea.lSection\n87101; regulation 18708.) Both of these narrowly construed eiceptions are fact-driven,\nand nothing in the facts you have provided would indicate that either of these exceptions\nwould apply to Supervisor Shoemaker's situafion. Accordingly, we have not analyzed\nthese excqrtions in relation to the facts you provided\nIf you have any other questions regarding this matter, please contact me at (916)\n322-5660.\nSincerelS\nLuisa Menchaca\nGeneral Counsel\n/\nBy:\nB. Armskong\nStaff Counsel, Legal Division\nEnclosure\nHBAjg\nI : \\Adviceltrs\\A-03 -006\n",
    "full_text_markdown": null
  },
  "parsed": {
    "date": "2003-03-11",
    "date_raw": "March 11,2003",
    "requestor_name": "Klein",
    "requestor_title": "County Counsel",
    "requestor_city": null,
    "document_type": "advice_letter"
  },
  "sections": {
    "question": "l. \nDoes Supervisor Shoemaker have a conflict of interest disqualifring him\nfrom making,particrpating in making or influencing a vote on the Ukiah Valley Area\nPlan (\"UVAP'), based on his economic interest in his personal residence and the\nimprovements to the access road to his residence that would accompany approval ofthe\nUVAP?\n2. \nDoes Supervisor Shoemaker have a conflict of interest disqualifring him\nfrom making, particrpating in making or influencing a vote on the UVAP, based o, his\neconomic interest in a client who is a source of income to him in excess of $500 over the\npast 12 months, and who has an option to purchase properfy within the UVAP area and\nseeks rezoning of that property from agricultural to residential for the building of low-\nincorne housing, or from the portion of the TIVAP dealing with that decision, if that\ndecision is segregated from the rest of the UVAP?\nrGovemmentCodesections8l000-91014. \nCommissionregulationsappearatTitle2,sectionsl8l0g-\n18997, ofthe California Code ofRegulations.\nffi\n3. \nDoes Supervisor Shoemakerhave a conflict of interest disqualifring him\nfrom making,particrpating in making or influencing a vote on the UVAP, based on his\neconomic interest in other clients within the TIVAP area who may be sources of income\nequal to or greaterthan $500 within the last 12 months?\n4. \nDoes Supervisor Shoemaker have a conflict of interest disqualiffing him\nfrom making, participatingin making or influencing a vote on the UVAP, based on his\neconomic interest in his business, Green Lion Landscape Services, which, among other\nthings, provides services to clients within the UVAP area?",
    "conclusion": "1. \nNo, unless it is reasonably foreseeable that the improvements to the access\nroad that would result from the development of the 80-acreparcel adjacent to his property\nwould have amaterial financial effect on the value of his properfy, sufficient to rebut the\npresumption o f non-m ateiality .\n2. \nYes. The rural housing development corporation initiated aproceeding\nbefore Supervisor Shoemaker's board and is a source of income in excess of $500 over\nthe past 12 months to him. Therefore, the corporation is directly involved in a\ngovernmental decision before Supervisor Shoemaker's board, and his conflict of interest\nis disqualiffing.\n3. \nPossibly, depending on the applicable materiality standard.\n4. \nNo. Supervisor Shoemakerhas determined that the materiality standard\napplicable to his business wjll not be met. Therefore, there is no disqualifyingconflict of\ninterest present related to Green Lion.",
    "facts": "The following facts were provided in your original letter and in subsequent\ntelephone conversations with Commission staffon March 10,2003.\nSupervisor Richard Shoemaker represents the2n District of Mendocino County.\nSupervisor Shoemaker has been a county supervisor for six years. IIis district is about\n7.5 square miles in a counQr of approximately 3,500 square miles in size. Roughly 80%\nof thepopulation of the 2\"d district lives within the boundaries of the City of Uiciah. The\nCity of tlkiah is wholly contained in the 2\"d district.\nThe county has undertaken the process of reviewing and possibly implementing\nthe Ukiah Valley Area Plan (\"UVAP'). This plan, when and if adopted, will be a part of\nthe Mendocino County General Plan. The City of Ukiah is excluded from the UVAP\nbecause the board of supervisors has no planning authority over the City of Ukiah.\n\n\nFileNo. ,4.-03-006\nThe UVAP is intended, when adopted, to provide comprehensive,long-term\npolicy direction for growth and development in the Ukiah Valley. The UVAP addresses\nfive of seven elements required by state law, excluding noise and housing. The three\nmajor elements of the plan are:\nResearch Elements: Open space and conservation, historic and archaeological\nsafety and energy.\nfnfrastructure Elements: Airport, community facilities and services, parks and\nrecreation, circulation and transportation.\nDevelopment Elements: Community design and land use.\nSupervisor Shoemaker owns a 1.Zi-aqeparcel within the city limits of Ukiah. It\nis his principal residence and the location of his landscape contracting business, He has\nowned this property since 1990. His property lies approximately 550 feet from aportion\nof the unincorporated county area included in the Ukiah Valley Area PIan.\nThere is an SO-acre parcel approximately 550 feet from Supervisor Shoemaker's\nreal property, which is currently undeveloped and is the subject of a possible zoning\ndesignation change in the UVAP.\nSupervisor Shoemaker's property is accessed by a substandard two-lane road at\nthis time. The road then continues through the SO-acre undeveloped parcel that would be\nincluded in the UVAP. The city has plans to widen the road and connect it to a main east-\nwest street 1,100 feet to the east. The UVAP will propose the county cooperate and\npafiicipate in this upgrade, through financial and regulatory support. It will then be\ndesignated as a main roadway connecting the only existing east-west corridor to a more\neasterly, shorter but important east-west corridor. As development occurs, road\nimprovement will be required to occur on at least TOYo of the road Supervisor\nShoemaker's property faces. The 70oh of the road on which improvernent will be\nrequired to occur will be the county portion of the road associated with the 80-acre\nparcel; Supervisor Shoemaker's property is fronted by aportion of the road owned by the\ncity.\nSupervisor Shoemaker also owns a landscape contracting company which is\noperated as a sole,proprietorship. This business provides installation and landscape\nmaintenance services. The business, Green Lion Landscape Services (\"Green Lion')\nprovides services to client properties within the UVAP area.\nA client of Green Lion, which, as clarified in ourMarch l0,2003,telephone\nconversation, is a source of income to Supervisor Shoemaker in excess of $500 over the\nTast 72 months, has an option agreernent to purchase real property in the UVAP are4\nwhich the client wants redesignated and rezoned from agricultural to residential. This\noption agreement has not yet been exercised. This client has also been in discussion with\nlandowners within 550 feet of Supervisor Shoemaker's real property to acquire that\nproperty. No agreernent has been entered into between these parties for that property.\nThis client is a rural housing development corporation, which acquires real property for\nresale to low-income persons. This corporation also assists low-income persons to build\nhouses on this property. The property and houses are owned, ultimatelS by persons other\nthan the development corporation. Neighboring property to the property for which an\noption to purchase exists, the Olga Hudson subdivision in the UVAP area, was aproperty\noriginally owned by the development corporation and is now owned by private residents.\nSupervisor Shoemaker does not provide landscaping services to residents of this\nsubdivision, nor does Supervisor Shoemakerprovide services to properties owned by the\ndevelopment corporation in the UVAP area.\nSupervisor Shoemakerprovides landscape services to other clients with real\nproperty ownership in the UVAP area, some of whom maybe sources of income equal to\nor in excess of $500 over the past 12 months, according to facts obtained by telephone on\nMarch 70,2003. With respect to these clients, Supervisor Shoemaker has represented\nthat no board of supervisor's decision involving action of the IIVAP, will result in an\nincrease or decrease in Green Lion's gross revenues for a fiscal year in the amount of\n$20,000 or more; nor will the board's decision result in Green Lion incurring or avoiding\nadditional expenses or reducing or eliminating existing expenses for a fiscal year in the\namount of $5,000 or more; nor will the board's decision result in an increase or decrease\nin the value of Green Lion's assets or liabilities of Green Lion by $20,000 ormore.\nAITALYSIS\nThe primary purpose for the conflict of interest provisions of the Act is to ensure\nthat \"[p]ublic officials, whether elected or appointed, [should] perform their duties in an\nimpartial manner, free from bias caused by their own financial interests or the financial\ninterests ofpersons who have supported them.\" (Section S1001(b).) In furtherance of\nthis goal, section 87100 of the Act prohibits a public official from making, participating\nin making, or otherwise using his or her official position to influence a governmental\ndecision in which the official has a financial interest.\nDetermining whether a conflict of interest exists under section 87100 requires",
    "analysis": "of the following questions as outlined below.2\nStep One: Is Supervisor Shoemaker a \"public officialrr?\nAs a member of the Mendocino County Board of Supervisors, Supervisor\nShoemaker is a \"mernber, officer, employee or consultant of a state or local government\nagency\" and, therefore, is subject to the conflict of interest provisions of the Act.\n(Section 82048; regulation 1 8701 (a).)\n' These questions are based on the Act's conflict-of-interest analysis provided at Regulation 18700(b).\nstep Two: rs supervisor shoemaker making, participating in making or\ninfluencing a governmental decision?\nAs a member of the board of supervisors, Supervisor Shoemaker will \"make a\ngovernmental decision\" if he votes on the UVAP. (Section 87l}l;regulations 18702 and\n18702.1.)\nStep Three: 'What are Supervisor Shoemaker's economic interests - \nthe possible\nsources of a conflict of interest?\nSection 87103 provides that apublic official has a \"financial interest\" in a\ngovernmental decision'lf it is reasonably foreseeable that the decision will have a\nmateriaT financial effect, distingu'ishable from its effect on thepublic generally,on the\nofficial, a member ofhis orher immediate family,\" or on any ofthe official's economic\ninterests, described as follows:\nA public official has an economic interest in a business entity in which he or she\nhas a direct orindirect investment 3 of $2,000 ormore (section 87103(a);\nRegulation 18703.1(a)); or in which he or she is a director, officer, parhrer,\ntrustee, employee, or holds any position of management (section 87103(d);\nregulation I 8703. 1(b));\na\na\nA public official has an economic interest in real property in which he or she has a\ndirect or indirect interest of $2,000 or more (section 87103(b); regulation\n187O3.2);\nA public official has an economic interest in.any source of income, including\npromised income, which aggregates to $500 ormore within 12 months prior to the\ndecision (section 87 I 03 (c); regulation I 87 03 .3);\nA public official has an economic interest in any source of gifts to him or her if\nthe gifts aggregate to $340 or more within 12 months prior to the decision\n(section 871 03(e); regulation 1870. .9;\nA public official has an economic interest in his or her personal finances,\nincluding those of his or her immediate family .. this is the \"personal financial\neffects\" rule (section 87103; regulation 13703,5).\nSupervisor Shoemaker has an economic interest in his personal residence and the\nsurrounding properfy, assuming he has a direct or indirect investment of $2,000 or more\nin the property and the strucfure. He has an economic interest in his business, Green Lion\n3 An indirect investment or interest means aoy investrnent or interest owned by the spouse of an official or\nby a mernber of the official's immediate family, by an agent on behalf of a public official, or by a business entity or\ntrust in which the official, the official's immediate family, or their agents own directly, indirectly, or beneficially a\nl0-percent interest or greater. (Section 87103.) \"Immediate family\" is defined at Section 820i9 as an official;s\nspouse and dependent children.\nLandscaping Services. Supervisor Shoemaker also has an economic interest in the\nunnamed client that is a rural housing development corporation (\"Development\nCorporation') that seeks therezoning of theproperty within the UVAP areato which it\nholds an option to purchase, as well as in any other clients who are sources of income\nequal to or in excess of $500 for the 12 months preceding the decision.\nStep f,'our: Are the economic interests of Supervisor Shoemaker directly or\nindirectly involved in the goyernmental decisions?\nReal Property\nReal property is directly involved in a govemmental decision if anypart of that\nreal property is located within 500 feet of the boundaries (orproposed boundaries) of the\nreal property which is the \"subject ofthe govemmental decision.,a\nSupervisor Shoemaker's property is located beyond 500 feet of the S0-acre parcel\nthat will be included within the UVAP, which presumptively makes the property\nindirectly involved. Under ordinary circumstances, this would be the end of the analysis\nas to whether Supervisor Shoemaker's property was directly or indirectly involved in the\ngovemmental decision. However, this is an unusual situation in which there is a\nsecondary decision imbedded within the larger decision that is even more significant to\nthe analysis than the larger decision.\nIn this case, the UVAP contains the proposal that the county \"cooperate\" with the\ncity in the improvement of the access road to Supervisor Shoemaker's residence, and\nover the course of the development of the 80-acre parcel ofproperty adjacent to\nSupervisor Shoemaker's land, approximately TOYo of the road Supervisor Shoemaker,s\nproperty faces, although not the portion directly in front ofhis property, will undergo\nimprovement, and the road will be designated a main roadway, and connecting it to an\nimportant east-west corridor.\nUnder these facts, because the county portion of the road that will be improved as\na result of development of the 80-acre parcel is the same 550 feet from his property as the\nS0-acre parcel, itself, Supervisor Shoemaker's property is indirectly involved in this\ndecision, as we11.5\nRegulation lSTW.2provides several other situations in which an official's real property is considered\n\"directly involved\" in a governmental decision. (lS7M.2(a)(2)-(6).) None of these appear to appiy to Supervisor\nShoemaker's facts.\n5 Regulation lS7}4.2(b)provides: \"(b) Notwithstanding subdivision (a) above, real property in which a\npublic official has an interest is not directly involved in a govemmental decision, but is indirecily involved if: . . . (2)\nThe decision solely concerns repairs, replacement, or maintenance of existing streets, water, sewer, storm drainage or\nsimilar facilities.\" This regulation does not apply to determine that Supervisor Shoemaker's property is indirectl!\ninvolved, because the decision at issue does not \"solely concem repairs, replacement, or maintenance\" of an existing\nroad. Rather, the road will be substantially improved as a result of the decision on the (IVAP, which will lead to\ndevelopment ofthe SO-acre parcel ofproperty adjacent to Supervisor shoemaker's properly.\nSources of Income and Supervisor Shoemakerrs Business\nThe same definition is applicable to sources of income and to business entities to\ndetermine whether they are directly or indirectly involved in a governmental decision.\nSet forth at regulation 18704.1(a)(1) and Q), it states:\n\"(a) A person, including business entities, sources of\nincome, and sources of gifts, is directly involved in a\ndecision before an official's agency when that person,\neither directly or by an agent:\n\"(I) Initiates the proceeding in which the decision will be\nmade by filing an application, claim, appeal, or similar\nrequest or;\n\"(2) Is a named party in, or is the subject o{, the\nproceeding conceming the decision before the official or\nthe official's agency. A person is the subject of a\nproceeding if a decision involves the issuance, renewal,\napproval, denial or revocation of any license, permit or\nother entitlement to, or contract with, the subject person.,,\nBased on this definition, the Development Corporation client is directly involved\nin the governmental decision, because it has initiated a proceeding to have property\nrezoned and redesignated from agricultural to residential. Any other sources of income to\nSupervisor Shoemaker who fall within the definition listed above would,likewise, be\ndirectly involved in a govemmental decision. For those sources ofincome.who have\nneither initiated a proceeding nor are the subject of a proceeding, as defined above, those\npersons are indirectly involved in the decision.\nLikewise, Supervisor Shoemaker's business, Green Lion Landscape Services, has\ninitiated no proceeding and is not a named party in,nor is the subject of the proceeding\nconcerning the UVAP decision, according to the facts with which we have been\npresented. Therefore, Green Lion is indirectly involved.\nSteps Five and Six: What are the applicable materiality standards and is it\nreasonably foreseeable that the financial effect of the governmental decision upon\nSupervisor Shoemaker's economic interests will meet these materiality standards?\nReal Property\nMateriality Standard: The financial effect of a govemmental decision on real\nproperty which is indirectly involved in the goveflrmental decision is presumed not to be\nmaterial. (Regulatio n 187 05.2@)( 1 ).) That regulation continues:\n\"This presumptiolnfi:u.y be rebutted byproof thatthere are\nspecific circumstances regarding the governmental\ndecision, its financial effect, and the nature of the real\nproperty in which the public official has an economic\ninterest, which make it reasonably foreseeable that the\ndecision will have amateial financial efi[ect on the real\nproperty in which the public official has an interest.\nExamples of specific circumstances that will be considered\nincludg but are not limited to, circumstances where the\ndecision aflects:\n\"(A) The development potential or income producing\npotential of the real property in which the official has an\neconomic interest;\n\"(B) The use of the real property in which the official has\nan economic interest;\n\"(C) The character of the neighborhood including, but not\nlimited to, substantial effects on: traffic, view, privacy,\nintensity ofuse, noise levels, air emissions, or similar traits\nof the neighborhood.\"\nIn considering these circumstances for rebuttal, it should be remembered that\nmaterial financial effect can mean either an increase or a decrease in property value or\nenjoyment for the owner/occupant of the property.\nIn this case, there may be some issues related to the road improvements and\nupgrades associated with the development of the S0-acre parcel adjacent to Supervisor\nShoemaker's property that may be sufficient to rebut the presumption of non-materiality.\nWe lack sufficient facts to analyze this issue further, but hightight the relevant regulations\nfor your review and analysis.\nSources of Income\nA. \nDevelopment Corporation: Because this source of income is directly\ninvolved in a govemmental decision before supavisor Shoemaker,s board, the\nmateriality standard set forth at regulation 18705.3(a) applies:\n\"Directly involved sources of income. Any reasonably\nforeseeable financial effect on a person who is a source of\nincome to a public official, and who is directly involved in\na decision before the official's agency, is deemed material.,,\nB. \nIndirectly fnvolved Sources of Ineome: Because these sources of\nincome are unidentified and unenumerated, this query having been added in ourMarch\n\n\nFile No. ,4.-03-006\n10,2003, telephone conversation, we can do no more than give a generaloverview of the\nregulations for your information. The materiality standardsfor this category of economic\ninterest can be found at regulation 18705.3(b) (copy encloseo. For indiiecily involved\nsources of income which are business entities, the materiality standards set forth in\nregulation 18705.1(c). This regulation sets forth a series ofmateriality thresholds, based\non the size of the business entity. For indirectly involved sogrces ofincome which are\nnon-profit entities, including governmental entities, regulation 18705.3(b)(2)(A)-(F) sets\nforth varying threshold amounts, depending on the entity's gross urr.rui i\"\"iiptr and the\nmeasurable financial effect of the decision on entity's income. For indirectly involved\nsources of income who are individuals:\n\"(3) . . . The effect of a decision is material as to an\nindividual who is a source ofincome to an official if any of\nthe following applies:\n\"(A) The decision will affect the individual,s income,\ninvestments or other tangible or intangible assets or\nliabilities (other than real property) by $1,000 or more; or\n\"(B) The decision will affect the individua|s rear property\ninterest in a manner that is considered material unaer iitte\n2, Califomia Code of Regulations, sections 1 g705.2(b).,,\nRegulation 18705.2(b), referenced above, sets forth the materiality standard for a public\nofficial's indirectly involved real property interests.\nSupervisor Shoemaker,s Business Enti8\nThe materiality standards for an indirectly involved business entity in which a\npublic official has an economic interest are found at regulation 18705.1(c), which sets\nforth varyrng materiality thresholds, based on the size of the business. dupervisor\nShoemaker has represented that \"no board of supervisor's decision involving action of\nthe UVAP, will result in an increase or decrease in Green Lion's gross reveriues for a\nfiscal year in the amount of $20,000 or more; nor will the board's decision result in\nGreen Lion incurring or avoiding additional expenses orreducing or eliminating existing\nexpenses for a fiscal year in the amount of $5,000 or more; nor will the board,s decision\nresult in an increase or decrease in the value of Green Lion's assets or liabilities of Green\nLion by $20,000 or more.\" Therefore, it appears that Supervisor Shoemaker has\nreviewed regulation 18705.1(c), and determined that his business is not covered by\nsubdivisions (c)(1)-(3), and that Green Lion falls into subdivision (c)(4) of regulation\n1 8705. 1, which provides:\n\"If the business entity is not covered by subdivisions (c)(l)-\n(3), the financial effect of a governmental decision on the\nbusiness entity is material if it is reasonably foreseeable\nthat:\n\n\nPageNo. l0\n\"(A) The governmental decision will result in an increase\nor decrease in the business entity's gross revenues for a\nfiscal year in the amount of $20,000 ormore; or,\n\"(B) The governmental decision will result in the business\nentity incurring or avoiding additional expenses or reducing\nor eliminating existing expenses for a fiscal year in the\namount of $5,000 or more; or,\n\"(C) The governmental decision will result in an increase\nor decrease in the value of the business entity,s assets or\nliabilities of $20,000 ormore.\"\nSupervisor Shoemakerhas determined that this materiality standard will not be\nmet.\nReasonable Foreseeability: An effect upon economic interests is considered\n\"reasonably foreseeable\" if there is a substantial likelihood that it will occur. (Regulation\n18706(a).) A financial effect need not be certain to be considered reasonably foreieeable,\nbut it must be more than a mere possibility. Qn re Thorner (1975) I FppC Ops. l9g.)\nThe determination of whether or not it is reasonably foreseeable that the\nmateriality standard will be met is necessarily a factual question that is ultimately for the\npublic official to decide.\nSegmentation of Decision: Please note that for purposes of determining\nconflicts of interest under the Act, governmental decisions are analyzed indepenJently to\ndetermine if there will be a foreseeable and material financial efiteci on apublic official,s\neconomic interest. (In re Owen (1976) 2 FPPC Ops.77.) Therefore, under certain\ncircumstances, a public official disqualified from one decision may participate in other\nrelated decisions, provided that the official's participation in the lattir does not affect the\ndecision in which he or she has a disqualifying conflict of interest. (SweeneyAdvice\nLetter, No. A-89-639.) Some decisions are too interrelated to be considered sqlarately so\nthat the official's conflict of interest on one decision will be disqualifting for the other.\n(Kilian Advice Letter, No. 4-89-522; Mtller Advice Letter, No. 4-82-11-9.) However, if\na governmental decision may be logically segregated, the public body maTrproceduraliy\nsegregate the decision prior to allowing the public official to participate.u -We \ndo not\n6 The Commission has previously advised public officials that the procedural segregation must include the\nfollowing three steps: (1) the decision in which the public official has a disqualifying fina-nci-al interest should be\nsegregated from the other decisions on the public body's agenda; (2) the decision-should be considered first and a final\ndecision should be reached without the disqualified official's participation; and (3) once a final decision has been\nreached, the disqualified ofificial may participate in the other decisions so tong as fils or her participation does not result\nin re-opening the previous decision, or in any other way affect the decision from which rtre ofnciaiwas disqualified.\n(Ennis Adice Letter, No. A-94-203.)\nhave enough information regarding the decisions before Supervisor Shoemaker to\ndetermine whether the segmentation procedure will be necessary or useful to him.\nSteps Seven and Eight: 66Public Generally\" and \"Legally Required participation,\nExceptions\nStep seven is an exception that applies when the reasonably foreseeable and\nmaterial financial effect on an official's economic interest is not distinguishable from the\neffect on the public generally. (Section 83ll2;regulation 18707.) Stei-eight is an\nexcqrtion that applies when the official's participation is legally requirea.lSection\n87101; regulation 18708.) Both of these narrowly construed eiceptions are fact-driven,\nand nothing in the facts you have provided would indicate that either of these exceptions\nwould apply to Supervisor Shoemaker's situafion. Accordingly, we have not analyzed\nthese excqrtions in relation to the facts you provided",
    "question_synthetic": null,
    "conclusion_synthetic": null,
    "extraction_method": "regex_validated",
    "extraction_confidence": 0.9500000000000001,
    "has_standard_format": true,
    "parsing_notes": "Mixed formats: modern, ocr"
  },
  "citations": {
    "government_code": [
      "82048",
      "87100",
      "87101",
      "87103",
      "87103(a)",
      "87103(b)",
      "87103(d)"
    ],
    "regulations": [
      "18700",
      "18702",
      "18703.1",
      "18704.1",
      "18705.1",
      "18705.2",
      "18705.3",
      "18706",
      "18707",
      "18708"
    ],
    "prior_opinions": [
      "A-89-522",
      "A-89-639",
      "A-94-203"
    ],
    "cited_by": [
      "08-214"
    ],
    "external": []
  },
  "classification": {
    "topic_primary": "conflicts_of_interest",
    "topic_secondary": null,
    "topic_tags": [],
    "confidence": 1.0,
    "classified_at": "2026-02-06T18:34:22.801388Z",
    "classification_method": "heuristic:citation_based"
  },
  "embedding": {
    "qa_text": "QUESTION: l. \nDoes Supervisor Shoemaker have a conflict of interest disqualifring him\nfrom making,particrpating in making or influencing a vote on the Ukiah Valley Area\nPlan (\"UVAP'), based on his economic interest in his personal residence and the\nimprovements to the access road to his residence that would accompany approval ofthe\nUVAP?\n2. \nDoes Supervisor Shoemaker have a conflict of interest disqualifring him\nfrom making, particrpating in making or influencing a vote on the UVAP, based o, his\neconomic interest in a client who is a source of income to him in excess of $500 over the\npast 12 months, and who has an option to purchase properfy within the UVAP area and\nseeks rezoning of that property from agricultural to residential for the building of low-\nincorne housing, or from the portion of the TIVAP dealing with that decision, if that\ndecision is segregated from the rest of the UVAP?\nrGovemmentCodesections8l000-91014. \nCommissionregulationsappearatTitle2,sectionsl8l0g-\n18997, ofthe California Code ofRegulations.\nffi\n3. \nDoes Supervisor Shoemakerhave a conflict of interest disqualifring him\nfrom making,particrpating in making or influencing a vote on the UVAP, based on his\neconomic interest in other clients within the TIVAP area who may be sources of income\nequal to or greaterthan $500 within the last 12 months?\n4. \nDoes Supervisor Shoemaker have a conflict of interest disqualiffing him\nfrom making, participatingin making or influencing a vote on the UVAP, based on his\neconomic interest in his business, Green Lion Landscape Services, which, among other\nthings, provides services to clients within the UVAP area?\n\nCONCLUSION: 1. \nNo, unless it is reasonably foreseeable that the improvements to the access\nroad that would result from the development of the 80-acreparcel adjacent to his property\nwould have amaterial financial effect on the value of his properfy, sufficient to rebut the\npresumption o f non-m ateiality .\n2. \nYes. The rural housing development corporation initiated aproceeding\nbefore Supervisor Shoemaker's board and is a source of income in excess of $500 over\nthe past 12 months to him. Therefore, the corporation is directly involved in a\ngovernmental decision before Supervisor Shoemaker's board, and his conflict of interest\nis disqualiffing.\n3. \nPossibly, depending on the applicable materiality standard.\n4. \nNo. Supervisor Shoemakerhas determined that the materiality standard\napplicable to his business wjll not be met. Therefore, there is no disqualifyingconflict of\ninterest present related to Green Lion.",
    "qa_source": "extracted",
    "first_500_words": "Re Feln PorrrrcAt. PnacrrcEs CouvrrssroN 428 J Street. Suite 620 . Sacramento, CA g5gl4-2329 (916) 322-5660. Fax (916) 322-0886 March 11,2003 H. Peter Klein, County Counsel Office of the County Counsel 501 Low Gap Road, Room 1030 Ukiah, CA95482 Your Request for Advice Our File No. A-03-006 Dear Mr. Klein: This letter is in response to your request for advice on behalf of Richard Shoemaker, Supervisor for the Second Diskict of the Mendocino County Board of Supervi.sors, regarding the conflict of interest provisions of the Political Reform Act (the 'Act').1 QUESTIONS l. Does Supervisor Shoemaker have a conflict of interest disqualifring him from making,particrpating in making or influencing a vote on the Ukiah Valley Area Plan (\"UVAP'), based on his economic interest in his personal residence and the improvements to the access road to his residence that would accompany approval ofthe UVAP? 2. Does Supervisor Shoemaker have a conflict of interest disqualifring him from making, particrpating in making or influencing a vote on the UVAP, based o, his economic interest in a client who is a source of income to him in excess of $500 over the past 12 months, and who has an option to purchase properfy within the UVAP area and seeks rezoning of that property from agricultural to residential for the building of low- incorne housing, or from the portion of the TIVAP dealing with that decision, if that decision is segregated from the rest of the UVAP? rGovemmentCodesections8l000-91014. CommissionregulationsappearatTitle2,sectionsl8l0g- 18997, ofthe California Code ofRegulations. ffi File No. 4-03-006 Page No. 2 3. Does Supervisor Shoemakerhave a conflict of interest disqualifring him from making,particrpating in making or influencing a vote on the UVAP, based on his economic interest in other clients within the TIVAP area who may be sources of income equal to or greaterthan $500 within the last 12 months? 4. Does Supervisor Shoemaker have a conflict of interest disqualiffing him from making, participatingin making or influencing a vote on the UVAP, based on his economic interest in his business, Green Lion Landscape Services, which, among other things, provides services to clients within the UVAP area? CONCLUSIONS 1. No, unless it is reasonably foreseeable that the improvements to the access road that would result from the development of the 80-acreparcel adjacent to his property would have amaterial financial effect on the value of his properfy, sufficient to rebut the presumption o f non-m ateiality . 2. Yes. The rural housing development corporation initiated aproceeding before Supervisor Shoemaker's board and is a source of income in excess of $500 over the past 12 months to him. Therefore, the corporation is directly involved in a governmental decision before Supervisor Shoemaker's board, and his conflict of interest is disqualiffing. 3. Possibly, depending on the applicable materiality standard. 4. No. Supervisor Shoemakerhas determined that the materiality standard applicable to his business wjll not be met. Therefore, there is no disqualifyingconflict of interest present related to Green Lion. FACTS The following facts were provided in your original letter and in subsequent",
    "summary": null
  }
}